{
    "manifest_version": 2,
    "name": "Moderator Toolbox-NXG for reddit",
    "author": "toolbox team",
    "short_name": "Toolbox-NXG",
    "description": "A set of tools to be used by moderators on reddit in order to make their jobs easier.",
    "version": "8.0.0.3",
    "version_name": "8.0.0: \"Forked Phoenix\"",
    "browser_specific_settings": {
        "gecko": {
            "id": "adhesivecheese@toolbox-team-nxg",
            "strict_min_version": "142.0",
            "data_collection_permissions": {
                "required": [
                    "none"
                ]
            }
        }
    },
    "permissions": [
        "https://*.reddit.com/",
        "https://old.reddit.com/",
        "https://oauth.reddit.com/",
        "cookies",
        "tabs",
        "storage",
        "unlimitedStorage",
        "notifications",
        "webNavigation",
        "alarms"
    ],
    "icons": {
        "16": "data/images/icon16.png",
        "48": "data/images/icon48.png",
        "128": "data/images/icon128.png"
    },
    "background": {
        "scripts": [
            "data/background/index.js"
        ],
        "persistent": true
    },
    "content_scripts": [
        {
            "run_at": "document_end",
            "all_frames": true,
            "matches": [
                "https://*.reddit.com/*"
            ],
            "exclude_matches": [
                "https://*.reddit.com/framedGild/*",
                "https://*.reddit.com/framedModal/*",
                "https://sh.reddit.com/report-flow/*",
                "https://*.reddit.com/chat/*",
                "https://*.reddit.com/account/sso/*",
                "https://ads.reddit.com/*",
                "https://*.reddit.com/*.json",
                "https://*.reddit.com/*.json?*",
                "https://*.reddit.com/*.json-html",
                "https://*.reddit.com/*.json-html?*"
            ],
            "css": [
                "data/modules/syntax/tbsyntax.css",
                "data/bundled.css"
            ],
            "js": [
                "data/init.js"
            ]
        }
    ],
    "web_accessible_resources": [
        "/data/bundled.css",
        "/data/MaterialSymbols-Filled.woff2"
    ]
}
